[
    {
        "rating": 9.97617,
        "thumbnail": "https://image-comic.pstatic.net/webtoon/765470/thumbnail/thumbnail_IMAG21_bcffdafe-27a8-4cfa-9f1c-973882c343f9.jpg",
        "id": "765470",
        "type": "웹툰",
        "platform": "네이버 웹툰",
        "title": "율리",
        "status": "토요웹툰",
        "genre": "드라마",
        "views": "-",
        "description": "신의 사원의 대도서관 관장인 쿠무치는 한 노예시장에서 율리라는 이름의 아이를 데려온다. \n사원의 일꾼 대신 율리에게 맡겨진 임무는 이웃나라로 함께 가서 사원의 지도자인 '하늘스승'의 후계자를 찾아 데려오는 것이다. \n쿠무치와 율리는 신의 사원을 나와 동쪽으로 떠나는 먼 길을 떠난다. \n두 사람은 여행길에 여러 다양한 사람들을 만나고 여러 나라를 거쳐 여행한다. \n그리고 그들은 드디어 찾고 있었던 '작은하늘스승'을 만나게 된다.",
        "keywords": [
            "과거",
            "드라마",
            "소년왕도물",
            "성장물",
            "모험",
            "소년물",
            "시대물",
            "신화",
            "동양",
            "세계관"
        ],
        "author": "돌배",
        "illustrator": "돌배",
        "original": "-",
        "age_rating": "전체연령가",
        "price": "무료",
        "favoriteCount": 73685,
        "url": "https://comic.naver.com/webtoon/list?titleId=765470",
        "episode": 86
    },
    {
        "rating": 9.95926,
        "thumbnail": "https://image-comic.pstatic.net/webtoon/677452/thumbnail/thumbnail_IMAG21_05f30a57-88b9-4798-8987-4851f1b28f5a.jpg",
        "id": "677452",
        "type": "웹툰",
        "platform": "네이버 웹툰",
        "title": "체크포인트",
        "status": "금요웹툰",
        "genre": "드라마",
        "views": "-",
        "description": "내 인생에 세이브 포인트가 있다면?\n하루에도 수십 번씩 시간을 되돌리는 남자.",
        "keywords": [
            "자본주의",
            "판타지",
            "머니게임",
            "드라마",
            "이능력",
            "타임슬립",
            "이능력배틀물",
            "회귀",
            "두뇌싸움"
        ],
        "author": "송가",
        "illustrator": "은소",
        "original": "-",
        "age_rating": "12세 이용가",
        "price": "무료",
        "favoriteCount": 309096,
        "url": "https://comic.naver.com/webtoon/list?titleId=677452",
        "episode": 115
    },
    {
        "thumbnail": "https://image-comic.pstatic.net/webtoon/780151/thumbnail/thumbnail_IMAG21_4062636529966659122.jpg",
        "rating": 9.78453,
        "id": "780151",
        "type": "웹툰",
        "platform": "네이버 웹툰",
        "title": "기밀입니다",
        "status": "8화 완결",
        "genre": "드라마",
        "views": "-",
        "description": "본 콘텐츠는 국가정보원의 브랜드 웹툰으로 시니, 광운 작가가 전하는 평범한 대학생의 리얼 스파이 체험기입니다.",
        "keywords": [
            "완결무료",
            "드라마",
            "완결드라마"
        ],
        "author": "시니",
        "illustrator": "광운",
        "original": "-",
        "age_rating": "전체연령가",
        "price": "무료",
        "favoriteCount": 5448,
        "url": "https://comic.naver.com/webtoon/list?titleId=780151",
        "episode": 8
    },
    {
        "thumbnail": "https://image-comic.pstatic.net/webtoon/761596/thumbnail/thumbnail_IMAG21_7089283062092215858.jpg",
        "rating": 9.90168,
        "id": "761596",
        "type": "웹툰",
        "platform": "네이버 웹툰",
        "title": "말하는대로",
        "status": "30화 완결",
        "genre": "드라마",
        "views": "-",
        "description": "꿈도 목표도 없이 하루하루를 살아가던 평범한 고등학교 3학년생 주현. \n어느 날부터 갑자기 그녀가 말하는 모든 것들이 실제로 이루어지게 된다.\n특별한 능력을 가지게 되었지만, 그만큼 말하는 것이 편하지만은 않은데... \n그녀의 평범하고 반복적이던 일상이 조금씩 뒤틀리기 시작한다!",
        "keywords": [
            "2020 지상최대공모전",
            "드라마",
            "완결드라마"
        ],
        "author": "무브",
        "illustrator": "무브",
        "original": "-",
        "age_rating": "전체연령가",
        "price": "24시간 기다리면 무료",
        "favoriteCount": 41156,
        "url": "https://comic.naver.com/webtoon/list?titleId=761596",
        "episode": 30
    },
    {
        "rating": 9.61171,
        "thumbnail": "https://image-comic.pstatic.net/webtoon/786932/thumbnail/thumbnail_IMAG21_7233456308666786353.jpg",
        "id": "786932",
        "type": "웹툰",
        "platform": "네이버 웹툰",
        "title": "바스키",
        "status": "58화 완결",
        "genre": "드라마",
        "views": "-",
        "description": "초능력자들이 벌인 300억짜리 은행강도 사건. \n이 사건으로 인해 한순간에 자신과 가족의 삶이 뒤틀려버린 한 남자의 사투가 시작된다.",
        "keywords": [
            "드라마",
            "완결드라마"
        ],
        "author": "진철수",
        "illustrator": "변기현",
        "original": "-",
        "age_rating": "15세 이용가",
        "price": "24시간 기다리면 무료",
        "favoriteCount": 9245,
        "url": "https://comic.naver.com/webtoon/list?titleId=786932",
        "episode": 58
    },
    {
        "thumbnail": "https://image-comic.pstatic.net/webtoon/400737/thumbnail/thumbnail_IMAG21_4050255823654434100.jpg",
        "rating": 9.73627,
        "id": "400737",
        "type": "웹툰",
        "platform": "네이버 웹툰",
        "title": "고삼이 집나갔다",
        "status": "64화 완결",
        "genre": "드라마",
        "views": "-",
        "description": "'집은 나갔지만 막나가진 않았습니다'\n대책없이 커져만가는 거짓말과 오해, 숨막히는 추격전\n수능을 앞둔 고3 수험생들의 REAL 가출기!",
        "keywords": [
            "드라마",
            "완결드라마"
        ],
        "author": "미티",
        "illustrator": "미티",
        "original": "-",
        "age_rating": "전체연령가",
        "price": "24시간 기다리면 무료",
        "favoriteCount": 177416,
        "url": "https://comic.naver.com/webtoon/list?titleId=400737",
        "episode": 64
    },
    {
        "thumbnail": "https://image-comic.pstatic.net/webtoon/824698/thumbnail/thumbnail_IMAG21_57d5031f-20e3-4092-8673-5cd9efd3fff7.jpg",
        "rating": 9.78487,
        "id": "824698",
        "type": "웹툰",
        "platform": "네이버 웹툰",
        "title": "로또 1등도 출근합니다",
        "status": "토요웹툰",
        "genre": "드라마",
        "views": "-",
        "description": "어디에서나 볼 수 있는 흔한 영업 직원 공은태,\n꿈에 그리던 로또 1등에 당첨되는데!\n\n세후 당첨 18억.\n큰 돈이지만, 인생을 역전시킬 정도의 대단한 금액인가?\n“살던 대로 살자…. 로또는 내 마음의 보험이라 생각하고.”\n\n든든한 보험을 안고 내질렀더니, \n하는 일마다 다 잘 되어 버린다?!\n\n오늘도 은태는 출근한다! 어제와는 다른 마음가짐으로.",
        "keywords": [
            "사이다",
            "소설원작",
            "판타지",
            "드라마",
            "인생역전",
            "현대",
            "직업드라마",
            "오피스",
            "지금추천작"
        ],
        "author": "서인하",
        "illustrator": "유극조",
        "original": "서인하",
        "age_rating": "12세 이용가",
        "price": "24시간 기다리면 무료",
        "favoriteCount": 106062,
        "url": "https://comic.naver.com/webtoon/list?titleId=824698",
        "episode": 50
    },
    {
        "thumbnail": "https://image-comic.pstatic.net/webtoon/797253/thumbnail/thumbnail_IMAG21_3adf296f-505b-4824-98b0-61c28432fb2d.jpg",
        "rating": 9.94381,
        "id": "797253",
        "type": "웹툰",
        "platform": "네이버 웹툰",
        "title": "메리의 불타는 행복회로",
        "status": "75화 완결",
        "genre": "드라마",
        "views": "-",
        "description": "음침한 여고생 유메리는 엄마의 절친이었던 천혜윤과 그의 아들 천사현과 함께 살고 있다.\n외모, 성적, 사교성, 모든 게 완벽한 그야말로 ‘엄마 친구 아들‘인 사현.\n사현과 결혼하여 진정한 가족이 되는 것을 꿈꾸는 메리는 과연 사현의 마음을 얻을 수 있을까?",
        "keywords": [
            "드라마",
            "완결드라마"
        ],
        "author": "김지수",
        "illustrator": "김지수",
        "original": "-",
        "age_rating": "전체연령가",
        "price": "24시간 기다리면 무료",
        "favoriteCount": 45148,
        "url": "https://comic.naver.com/webtoon/list?titleId=797253",
        "episode": 75
    },
    {
        "thumbnail": "https://image-comic.pstatic.net/webtoon/678497/thumbnail/thumbnail_IMAG21_3702862912262911333.jpg",
        "rating": 9.8364,
        "id": "678497",
        "type": "웹툰",
        "platform": "네이버 웹툰",
        "title": "오렌지 모멘트",
        "status": "25화 완결",
        "genre": "드라마",
        "views": "-",
        "description": "본 컨텐츠는 한화이글스의 브랜드 웹툰으로 글 해마작가, 그림 억수씨 작가가 전하는 오렌지모멘트 입니다.\n\r\n100번넘는 취업의 고배를 마시고 어렵게 취업한곳은 바로 한화이글스 야구단\n\r\n야알못 양혜진이 야구단에서 살아남기 위해 좌충우돌 펼쳐지는 스펙타클 이야기",
        "keywords": [
            "완결무료",
            "드라마",
            "완결드라마",
            "야구"
        ],
        "author": "해마",
        "illustrator": "억수씨",
        "original": "-",
        "age_rating": "전체연령가",
        "price": "무료",
        "favoriteCount": 15389,
        "url": "https://comic.naver.com/webtoon/list?titleId=678497",
        "episode": 25
    },
    {
        "rating": 9.97173,
        "thumbnail": "https://image-comic.pstatic.net/webtoon/801505/thumbnail/thumbnail_IMAG21_1ba4c85a-5a9f-41aa-af97-6c514f220b44.jpg",
        "id": "801505",
        "type": "웹툰",
        "platform": "네이버 웹툰",
        "title": "뮤즈 온 유명",
        "status": "97화 완결",
        "genre": "드라마",
        "views": "-",
        "description": "\"부업은 청소도우미, 본업은 무명 배우. 아이러니하게도 내 이름은 유명이다.\" 유난히 힘들던 날, 우연히 거장의 사진전에 들어간 무명배우 유명은 자신의 사진을 보게 된다. 그 사진들은 유명이 제일 빛나던 시절을 담고 있었고, 그런 모습은 지금의 유명과는 정반대였다. 유명은 알 수 없는 사진작가의 뮤즈로 스타가 될 수 있을까.",
        "keywords": [
            "예술",
            "공식미녀",
            "하이퍼리얼리즘",
            "공식미남",
            "청춘로맨스",
            "다정남",
            "삼각관계",
            "청춘",
            "연예계",
            "드라마",
            "능력녀",
            "완결드라마",
            "재회",
            "연예계로맨스",
            "능력남",
            "전남친"
        ],
        "author": "수진",
        "illustrator": "수진",
        "original": "-",
        "age_rating": "15세 이용가",
        "price": "24시간 기다리면 무료",
        "favoriteCount": 334138,
        "url": "https://comic.naver.com/webtoon/list?titleId=801505",
        "episode": 97
    },
    {
        "rating": 9.392,
        "thumbnail": "https://image-comic.pstatic.net/webtoon/780266/thumbnail/thumbnail_IMAG21_7004002542814586168.jpg",
        "id": "780266",
        "type": "웹툰",
        "platform": "네이버 웹툰",
        "title": "당신의 여자가 되고 싶어요",
        "status": "54화 완결",
        "genre": "로맨스",
        "views": "-",
        "description": "성하윤 마음 속 갖고싶은 남자 1위, 문신휘!\n다정하지만 연애에 있어서 만큼은 철벽남 신휘를 얻기 위한\n계략녀 하윤의 맹랑 발칙한 계획들이 펼쳐진다.\n\n생각은 짧게. 행동은 빠르게!\n철옹성을 함락하기 위한 고군분투 로맨스",
        "keywords": [
            "소설원작",
            "로맨스",
            "완결로맨스"
        ],
        "author": "팀 아가페",
        "illustrator": "팀 아가페",
        "original": "별규",
        "age_rating": "12세 이용가",
        "price": "24시간 기다리면 무료",
        "favoriteCount": 57198,
        "url": "https://comic.naver.com/webtoon/list?titleId=780266",
        "episode": 54
    },
    {
        "thumbnail": "https://image-comic.pstatic.net/webtoon/710748/thumbnail/thumbnail_IMAG21_7017792614173860918.jpg",
        "rating": 9.97503,
        "id": "710748",
        "type": "웹툰",
        "platform": "네이버 웹툰",
        "title": "호러와 로맨스",
        "status": "75화 완결",
        "genre": "로맨스",
        "views": "-",
        "description": "사랑을 알고 싶은 호러 작가와 \n공포물은 질색인 인기 로맨스 작가의 \n오싹달콤한 로맨스 제작기",
        "keywords": [
            "로맨스",
            "완결로맨스"
        ],
        "author": "루시드",
        "illustrator": "루시드",
        "original": "-",
        "age_rating": "전체연령가",
        "price": "24시간 기다리면 무료",
        "favoriteCount": 118425,
        "url": "https://comic.naver.com/webtoon/list?titleId=710748",
        "episode": 75
    },
    {
        "thumbnail": "https://image-comic.pstatic.net/webtoon/824888/thumbnail/thumbnail_IMAG21_6fbbf8b5-b197-4abe-9602-61c6cdbc4dba.jpg",
        "rating": 9.92951,
        "id": "824888",
        "type": "웹툰",
        "platform": "네이버 웹툰",
        "title": "이기적 연애론",
        "status": "수요웹툰",
        "genre": "로맨스",
        "views": "-",
        "description": "\"넌 어떨까? 내가 다른 남자와 행복하게 있는 걸 보면.\" 평범한 30대인 '유민'과 '현도'. 모종의 이유로 각자의 연인에게 헤어짐을 고했지만, 사실은 누구보다 미련이 넘치는 두 사람. 전 연인이 자신을 붙잡아 줬으면 하는 이기적인 마음이 통한 두 사람은 '계획'을 세운다. 그건 바로, 가짜 데이트를 하며 서로의 전 연인을 자극해 보는 것! 이기적이고 어리석은 이들의 계획은 성공할 수 있을까?",
        "keywords": [
            "청춘",
            "로맨스",
            "까칠남",
            "무심남",
            "오피스로맨스",
            "리얼로맨스",
            "청춘로맨스",
            "감성적인",
            "전남친",
            "계약연애"
        ],
        "author": "교교박",
        "illustrator": "교교박",
        "original": "-",
        "age_rating": "12세 이용가",
        "price": "무료",
        "favoriteCount": 261280,
        "url": "https://comic.naver.com/webtoon/list?titleId=824888",
        "episode": 39
    },
    {
        "thumbnail": "https://image-comic.pstatic.net/webtoon/828945/thumbnail/thumbnail_IMAG21_7ae4bdf6-ae4b-4e15-9e47-478b0eed1ebd.jpg",
        "rating": 9.95055,
        "id": "828945",
        "type": "웹툰",
        "platform": "네이버 웹툰",
        "title": "남주 좀 납치합시다!",
        "status": "수요웹툰",
        "genre": "로맨스",
        "views": "-",
        "description": "나는 비비안.\n친구가 쓴 소설 속에 빙의했다.\n그것도 남주를 납치하고 죽는 조연으로.\n납치를 하지 않으면 세계가 멸망한다는데 별 수 있나?\n남주를 납치해서 알뜰살뜰하게 보살펴서 목숨을 보전해 보자!\n라고 패기롭게 시작했으나... 나는 남주의 얼굴을 모른다.\n에라이 모르겠다.\n잘생긴 사람 중 한명은 남주겠지!\n근데 내가 악역이랑 여주인공을 납치해 버린 것 같다.\n너희들이 왜 거기서 나와?",
        "keywords": [
            "햇살남",
            "얼빠녀",
            "로판",
            "악역이주인공",
            "가벼운",
            "명랑녀",
            "빙의",
            "개그",
            "공식미남",
            "왕족/귀족",
            "힐링",
            "서양",
            "다정남",
            "소설원작",
            "로맨스",
            "능력녀",
            "능글남"
        ],
        "author": "조난",
        "illustrator": "조난",
        "original": "단시오",
        "age_rating": "전체연령가",
        "price": "24시간 기다리면 무료",
        "favoriteCount": 40009,
        "url": "https://comic.naver.com/webtoon/list?titleId=828945",
        "episode": 39
    },
    {
        "rating": 9.92098,
        "thumbnail": "https://image-comic.pstatic.net/webtoon/809558/thumbnail/thumbnail_IMAG21_094f39f0-92cf-434d-9578-10b896b79ffb.jpg",
        "id": "809558",
        "type": "웹툰",
        "platform": "네이버 웹툰",
        "title": "나랑 해요",
        "status": "58화 완결",
        "genre": "로맨스",
        "views": "-",
        "description": "정략결혼을 앞둔 주원 호텔 후계자 하경. 약혼식 3주 전, 청혼을 받는다. 결혼 상대가 아닌 다른 남자에게서.\n심지어 그는 약혼자의 동생이었다.\n“우리 형이랑 결혼 못 해요. 내가 못 하게 할 거니까.” \n10대 때의 첫 일탈을 함께한 그와 또 한번 인생 최대의 일탈을 하게 될 것만 같은, 불길한 예감이 들기 시작했다.",
        "keywords": [
            "소설원작",
            "로맨스",
            "고자극로맨스",
            "재벌",
            "리얼로맨스",
            "직진남",
            "완결로맨스",
            "자극적인",
            "다정남",
            "짝사랑"
        ],
        "author": "통조림",
        "illustrator": "통조림",
        "original": "별규",
        "age_rating": "12세 이용가",
        "price": "24시간 기다리면 무료",
        "favoriteCount": 40267,
        "url": "https://comic.naver.com/webtoon/list?titleId=809558",
        "episode": 58
    },
    {
        "rating": 9.95862,
        "thumbnail": "https://image-comic.pstatic.net/webtoon/797184/thumbnail/thumbnail_IMAG21_55173cb1-1941-4875-abb5-cc7d8be0c74b.jpg",
        "id": "797184",
        "type": "웹툰",
        "platform": "네이버 웹툰",
        "title": "대충 캠퍼스로맨스임",
        "status": "토요웹툰",
        "genre": "로맨스",
        "views": "-",
        "description": "평범한 대학생 하윤. 갑자기 떠난 여행에서 강온을 마주친다. \n강온은 하윤에게 한눈에 반하여 고백을 하지만, 하윤은 그를 거절한다. \n그리고  다신 볼 일 없을 것이라 생각했던 둘은 학교 동아리 모집기간에 재회하게 되는데..! \n어라? 어쩌다보니 동아리 '그대'에 같이 들어가고, 에? '그대'의 회장 지일 마저 하윤을 좋아한다고?! ㅋㅋ이거 망상 아님. 진짜임.",
        "keywords": [
            "가벼운",
            "명랑녀",
            "리얼로맨스",
            "유혹남",
            "캠퍼스",
            "직진남",
            "청춘로맨스",
            "공감",
            "다정남",
            "삼각관계",
            "청춘",
            "로맨스",
            "능글남",
            "로맨틱코미디",
            "순정남",
            "캠퍼스로맨스"
        ],
        "author": "공철진",
        "illustrator": "공철진",
        "original": "-",
        "age_rating": "15세 이용가",
        "price": "무료",
        "favoriteCount": 348698,
        "url": "https://comic.naver.com/webtoon/list?titleId=797184",
        "episode": 120
    },
    {
        "rating": 9.92015,
        "thumbnail": "https://image-comic.pstatic.net/webtoon/700843/thumbnail/thumbnail_IMAG21_593090a1-a46f-463f-9b83-93e892c5636d.jpg",
        "id": "700843",
        "type": "웹툰",
        "platform": "네이버 웹툰",
        "title": "우리 오빠는 아이돌",
        "status": "128화 완결",
        "genre": "로맨스",
        "views": "-",
        "description": "덕계못이라고?! 집념의 덕후 남다름, 오빠의 회사에 취직하다!",
        "keywords": [
            "아이돌",
            "삼각관계",
            "로맨스",
            "연예계",
            "오피스로맨스",
            "완결로맨스",
            "사내연애"
        ],
        "author": "성은",
        "illustrator": "성은",
        "original": "-",
        "age_rating": "전체연령가",
        "price": "24시간 기다리면 무료",
        "favoriteCount": 345697,
        "url": "https://comic.naver.com/webtoon/list?titleId=700843",
        "episode": 128
    },
    {
        "rating": 9.96704,
        "thumbnail": "https://image-comic.pstatic.net/webtoon/802079/thumbnail/thumbnail_IMAG21_a30fbbcb-33ac-4b24-aa8d-0049007595e0.jpg",
        "id": "802079",
        "type": "웹툰",
        "platform": "네이버 웹툰",
        "title": "청춘계시록",
        "status": "휴재",
        "genre": "로맨스",
        "views": "-",
        "description": "사이비 교주 아들과의 아슬아슬하고 위험천만한 동거가 시작됐다! 철석같이 믿었던 외삼촌에게 사기를 당한 청아네. 부모님은 행방불명된 외삼촌을 쫓는다며 사라지고, 청아는 갑작스레 빈 집에 혼자 살게 된다. 그런데 사기당한 가족이 청아네만이 아니었으니! 자치구에서 가장 큰 사이비, ‘천년재림교’도 외삼촌에게 제대로 속았다. 그리고 청아네 집에 찾아온 교주의 아들 ‘요한’. 무작정 짐을 끌고 쳐들어오는데...! 신이시여, 이 동거 괜찮을까요?",
        "keywords": [
            "하이틴",
            "사이비종교",
            "청춘",
            "로맨스",
            "학원물",
            "청춘로맨스",
            "로맨틱코미디",
            "학원로맨스",
            "친구>연인"
        ],
        "author": "한서",
        "illustrator": "한서",
        "original": "-",
        "age_rating": "15세 이용가",
        "price": "무료",
        "favoriteCount": 507563,
        "url": "https://comic.naver.com/webtoon/list?titleId=802079",
        "episode": 101
    },
    {
        "thumbnail": "https://image-comic.pstatic.net/webtoon/793853/thumbnail/thumbnail_IMAG21_f4d3c4d2-b594-4123-925e-e141fdebd4da.jpg",
        "rating": 9.96666,
        "id": "793853",
        "type": "웹툰",
        "platform": "네이버 웹툰",
        "title": "악마라고 불러다오",
        "status": "금요웹툰",
        "genre": "로맨스",
        "views": "-",
        "description": "낮에는 성형외과 의사로, 밤에는 악마로 살아가는 '현신'.  \n눈빛만으로 누구든 유혹하는 마력을 가졌지만,\n어느 날 나타난 '이나'에게는 유혹이 통하지 않는다.\n대신 태평한 얼굴로 가슴 수술을 해달라 하는데... 이 여자는 뭘까?",
        "keywords": [
            "판타지",
            "로판",
            "구원서사",
            "치명적인",
            "가벼운",
            "현대",
            "명랑녀",
            "유혹남",
            "혐관",
            "공식미남",
            "소설원작",
            "로맨스",
            "까칠남",
            "철벽녀",
            "인외존재",
            "사연녀",
            "혐관로맨스"
        ],
        "author": "자양",
        "illustrator": "써나",
        "original": "안테",
        "age_rating": "15세 이용가",
        "price": "무료",
        "favoriteCount": 154119,
        "url": "https://comic.naver.com/webtoon/list?titleId=793853",
        "episode": 128
    },
    {
        "rating": 9.94333,
        "thumbnail": "https://image-comic.pstatic.net/webtoon/812414/thumbnail/thumbnail_IMAG21_671e844b-2049-4d5a-953b-bb54b7b02c00.jpg",
        "id": "812414",
        "type": "웹툰",
        "platform": "네이버 웹툰",
        "title": "포 더 퀸덤",
        "status": "휴재",
        "genre": "로맨스",
        "views": "-",
        "description": "악마 아벨은 인간 여자 연리에게 사랑하는 형, 카인을 잃고 만다.\n분노에 가득 차 연리를 찾아간 아벨은 사랑에 빠지는 금총알을 맞게 되면서, 연리에게 끓어오르는 사랑을 느끼게 되는데…\n그는 과연 형제의 복수를 택할 것인가? 아니면 원수와의 냉혹한 사랑을 택할 것인가?",
        "keywords": [
            "공식미녀",
            "판타지",
            "치명적인",
            "현대",
            "성인웹툰",
            "신화",
            "걸크러시",
            "로맨스",
            "연예계",
            "고자극로맨스",
            "능력녀",
            "인외존재",
            "사연녀",
            "자극적인",
            "혐관로맨스"
        ],
        "author": "로즈옹",
        "illustrator": "로즈옹",
        "original": "-",
        "age_rating": "18세 이용가",
        "price": "무료",
        "favoriteCount": 128074,
        "url": "https://comic.naver.com/webtoon/list?titleId=812414",
        "episode": 80
    },
    {
        "thumbnail": "https://image-comic.pstatic.net/webtoon/833255/thumbnail/thumbnail_IMAG21_504f6152-8a60-42a0-a1c0-43cd77f9c430.jpg",
        "rating": 9.95754,
        "id": "833255",
        "type": "웹툰",
        "platform": "네이버 웹툰",
        "title": "낢이 사는 이야기 - 계속되는 미미한 인생",
        "status": "화, 토 연재",
        "genre": "일상",
        "views": "-",
        "description": "혼란의 도가니인 인생에 잘 모르겠는 것 투성이지만, 오늘도 그저 슬렁슬렁 살아가 본다. \n고양이들과 함께 창밖 구경, 꽃 구경을 하며 울고 웃고 먹고 마시는 방구석 인생. \n올해로 연재 20년차를 맞이하는, 낢의 미미하고 사소한 이야기.",
        "keywords": [
            "연애/결혼공감",
            "일상개그힐링",
            "가족",
            "가벼운",
            "동물",
            "개그",
            "힐링",
            "일상"
        ],
        "author": "서나래",
        "illustrator": "서나래",
        "original": "-",
        "age_rating": "전체연령가",
        "price": "무료",
        "favoriteCount": 94644,
        "url": "https://comic.naver.com/webtoon/list?titleId=833255",
        "episode": 37
    },
    {
        "rating": 9.91918,
        "thumbnail": "https://image-comic.pstatic.net/webtoon/317365/thumbnail/thumbnail_IMAG21_3906082562554214707.jpg",
        "id": "317365",
        "type": "웹툰",
        "platform": "네이버 웹툰",
        "title": "고시생툰",
        "status": "56화 완결",
        "genre": "일상",
        "views": "-",
        "description": "대학입학. 그로부터 몇 년. \n\r\n공부하는 우리들의 빛나는 청춘.",
        "keywords": [
            "완결일상",
            "완결무료",
            "일상"
        ],
        "author": "seri",
        "illustrator": "seri",
        "original": "-",
        "age_rating": "전체연령가",
        "price": "무료",
        "favoriteCount": 43791,
        "url": "https://comic.naver.com/webtoon/list?titleId=317365",
        "episode": 56
    },
    {
        "rating": 9.85971,
        "thumbnail": "https://image-comic.pstatic.net/webtoon/758659/thumbnail/thumbnail_IMAG21_e0d1374e-803b-4be3-b45c-6e4d1f4d9164.jpg",
        "id": "758659",
        "type": "웹툰",
        "platform": "네이버 웹툰",
        "title": "오빠세끼",
        "status": "목요웹툰",
        "genre": "일상",
        "views": "-",
        "description": "우리학교 인기남 3인방이 누군가에게는 노답 친오빠!?\n주목받는건 질색! 조용하고 존재감 없는 평범한 삶을 추구하는 해주에게는 걸어만 다녀도 튀게 잘생긴 오빠들이 있다.\n해주는 오빠들의 동생임을 숨기며 학교를 다니지만, 결국 들켜버리게 되는데...\n과연 해주는 오빠들이 있는 학교에서 자신의 목표를 이룰수 있을까?",
        "keywords": [
            "하이틴",
            "삼각관계",
            "일상",
            "학원로맨스"
        ],
        "author": "올리브유",
        "illustrator": "올리브유",
        "original": "-",
        "age_rating": "전체연령가",
        "price": "무료",
        "favoriteCount": 299208,
        "url": "https://comic.naver.com/webtoon/list?titleId=758659",
        "episode": 71
    },
    {
        "thumbnail": "https://image-comic.pstatic.net/webtoon/150389/thumbnail/thumbnail_IMAG21_7378639139746570548.jpg",
        "rating": 9.94131,
        "id": "150389",
        "type": "웹툰",
        "platform": "네이버 웹툰",
        "title": "스마일브러시",
        "status": "39화 완결",
        "genre": "일상",
        "views": "-",
        "description": "반복되는 일상에서 발생하는 사건 사고들.\n\r\n소심하지만 할 말은 하는 가슴 따스한 와루의 좌충우돌 일상의 반전 에피소드.",
        "keywords": [
            "완결일상",
            "완결무료",
            "일상"
        ],
        "author": "와루",
        "illustrator": "와루",
        "original": "-",
        "age_rating": "전체연령가",
        "price": "무료",
        "favoriteCount": 13549,
        "url": "https://comic.naver.com/webtoon/list?titleId=150389",
        "episode": 39
    },
    {
        "thumbnail": "https://image-comic.pstatic.net/webtoon/755642/thumbnail/thumbnail_IMAG21_3630520553252872754.jpg",
        "rating": 9.95837,
        "id": "755642",
        "type": "웹툰",
        "platform": "네이버 웹툰",
        "title": "내일을 부탁해",
        "status": "8화 완결",
        "genre": "일상",
        "views": "-",
        "description": "본 컨텐츠는 통계청의 브랜드 웹툰으로 이혜 작가와 자까 작가가 전하는 2020 인구주택총조사 & 농림어업총조사 캠페인입니다.",
        "keywords": [
            "완결일상",
            "완결무료",
            "일상"
        ],
        "author": "자까",
        "illustrator": "자까",
        "original": "-",
        "age_rating": "전체연령가",
        "price": "무료",
        "favoriteCount": 23796,
        "url": "https://comic.naver.com/webtoon/list?titleId=755642",
        "episode": 8
    },
    {
        "rating": 9.8152,
        "thumbnail": "https://image-comic.pstatic.net/webtoon/643548/thumbnail/thumbnail_IMAG21_3760568603236394340.jpg",
        "id": "643548",
        "type": "웹툰",
        "platform": "네이버 웹툰",
        "title": "낢 따라 해봐요",
        "status": "8화 완결",
        "genre": "일상",
        "views": "-",
        "description": "낢이 전해주는 스마트한 학교생활과 백수탈출성공기!\n과연 낢은 백수생활에서 벗어나 꿈꾸는 직업을 찾고 엄마의 잔소리에서 벗어날 수 있을까?\n본 컨텐츠는<낢이야기>의 서나래 작가가 전하는 세종사이버대학교의 브랜드 웹툰입니다.",
        "keywords": [
            "완결일상",
            "완결무료",
            "일상"
        ],
        "author": "서나래",
        "illustrator": "서나래",
        "original": "-",
        "age_rating": "전체연령가",
        "price": "무료",
        "favoriteCount": 13971,
        "url": "https://comic.naver.com/webtoon/list?titleId=643548",
        "episode": 8
    },
    {
        "thumbnail": "https://image-comic.pstatic.net/webtoon/801481/thumbnail/thumbnail_IMAG21_2bea3c4d-d135-413a-9729-ac594e6925f0.jpg",
        "rating": 9.79447,
        "id": "801481",
        "type": "웹툰",
        "platform": "네이버 웹툰",
        "title": "소장",
        "status": "8화 완결",
        "genre": "일상",
        "views": "-",
        "description": "누구나 주변 사람들에게 완전히 이해받지 못할 자기만의 소장용 세계가 있다.\n이 쓸모없는 행위가 왜 필요한지, 왜 계속되어야 하는지, 그리고 어떤 세상은 이 쓸모없음으로 비로소 생존하고 있음을 말하는 이야기!",
        "keywords": [
            "완결일상",
            "일상"
        ],
        "author": "소영",
        "illustrator": "소영",
        "original": "-",
        "age_rating": "전체연령가",
        "price": "24시간 기다리면 무료",
        "favoriteCount": 8712,
        "url": "https://comic.naver.com/webtoon/list?titleId=801481",
        "episode": 8
    },
    {
        "rating": 9.63356,
        "thumbnail": "https://image-comic.pstatic.net/webtoon/80536/thumbnail/thumbnail_IMAG21_3703755716405966945.jpg",
        "id": "80536",
        "type": "웹툰",
        "platform": "네이버 웹툰",
        "title": "다섯작가의 이런저런이야기",
        "status": "20화 완결",
        "genre": "일상",
        "views": "-",
        "description": "본 컨텐츠는 GM대우 홍보용 웹툰입니다.\n조석, 김규삼, 네스티켓, 귀귀, 무적핑크! 대한민국을 대표하는 다섯 작가들의 이런저런 이야기들!",
        "keywords": [
            "완결일상",
            "완결무료",
            "일상"
        ],
        "author": "네이버웹툰 작가",
        "illustrator": "네이버웹툰 작가",
        "original": "-",
        "age_rating": "전체연령가",
        "price": "무료",
        "favoriteCount": 1032,
        "url": "https://comic.naver.com/webtoon/list?titleId=80536",
        "episode": 20
    },
    {
        "rating": 9.9812,
        "thumbnail": "https://image-comic.pstatic.net/webtoon/834886/thumbnail/thumbnail_IMAG21_3a360149-06bd-4238-b9b6-5b4e6dc80420.jpg",
        "id": "834886",
        "type": "웹툰",
        "platform": "네이버 웹툰",
        "title": "노곤하개 쇼츠",
        "status": "월, 목 연재",
        "genre": "일상",
        "views": "-",
        "description": "이제는 개 셋! 고양이 셋! \n6마리의 동물들과 함께 사는 일상은 과연 어떨까?!",
        "keywords": [
            "일상"
        ],
        "author": "홍끼",
        "illustrator": "홍끼",
        "original": "-",
        "age_rating": "전체연령가",
        "price": "무료",
        "favoriteCount": 61107,
        "url": "https://comic.naver.com/webtoon/list?titleId=834886",
        "episode": 20
    },
    {
        "rating": 9.95011,
        "thumbnail": "https://image-comic.pstatic.net/webtoon/25613/thumbnail/thumbnail_IMAG21_3688790263676941156.jpg",
        "id": "25613",
        "type": "웹툰",
        "platform": "네이버 웹툰",
        "title": "생활의참견",
        "status": "1001화 완결",
        "genre": "일상",
        "views": "-",
        "description": "쉽게 지나치는 일상과 지나간 추억 속에서 발견하는 유쾌한 웃음,\n삶의 유머를 녹여낸 황당유쾌추억생활만화!",
        "keywords": [
            "완결일상",
            "일상"
        ],
        "author": "김양수",
        "illustrator": "김양수",
        "original": "-",
        "age_rating": "전체연령가",
        "price": "24시간 기다리면 무료",
        "favoriteCount": 211101,
        "url": "https://comic.naver.com/webtoon/list?titleId=25613",
        "episode": 1001
    },
    {
        "rating": 9.7049,
        "thumbnail": "https://image-comic.pstatic.net/webtoon/835423/thumbnail/thumbnail_IMAG21_dd82370b-a77f-4410-b865-cbcb0f0058b9.jpg",
        "id": "835423",
        "type": "웹툰",
        "platform": "네이버 웹툰",
        "title": "던전짐꾼",
        "status": "일요웹툰",
        "genre": "판타지",
        "views": "-",
        "description": "타고난 재능을 가진 자들만이 던전을 토벌하는 모험가가 될 수 있는 세계.\n세상은 '나기'를 모험가가 될 수 없는 짐꾼으로 규정했다.\n\n하지만 던전을 클리어 하면 그게 모험가잖아?\n\n전투 스킬 0! 생존 능력 만렙!\n운명을 거스르는 만능 짐꾼 나기의 던전 정복기!",
        "keywords": [
            "판타지",
            "중세판타지액션",
            "소년왕도물",
            "이능력",
            "모험",
            "소년물",
            "액션판타지",
            "마법",
            "용사",
            "크리처",
            "우정"
        ],
        "author": "나진수",
        "illustrator": "나진수",
        "original": "-",
        "age_rating": "15세 이용가",
        "price": "무료",
        "favoriteCount": 14589,
        "url": "https://comic.naver.com/webtoon/list?titleId=835423",
        "episode": 8
    },
    {
        "thumbnail": "https://image-comic.pstatic.net/webtoon/823536/thumbnail/thumbnail_IMAG21_4b4cdcf1-2795-40c4-b8d5-09b209638708.jpg",
        "rating": 9.8568,
        "id": "823536",
        "type": "웹툰",
        "platform": "네이버 웹툰",
        "title": "요리사가 되고 싶은 천마님",
        "status": "월요웹툰",
        "genre": "판타지",
        "views": "-",
        "description": "몬스터 게이트 사건으로 자신의 전생을 깨달은 우진.\n그는.. 중원을 재패한 천마였다!\n천마였던 당시에도 이루지 못한 꿈이 있었으니..\n이번에는 반드시 이루고 말리라.\n\n요리사라는 꿈을! \n전생 천마 '천우진'이 요리사가 되기 위한 위대한(?) 이야기!",
        "keywords": [
            "판타지",
            "헌터물",
            "악역이주인공",
            "가벼운",
            "이세계요리",
            "던전물",
            "상태창",
            "액션",
            "소설원작",
            "인외존재",
            "이능력",
            "먼치킨",
            "차원이동",
            "크리처",
            "환생"
        ],
        "author": "필나르",
        "illustrator": "춘삼",
        "original": "점도리",
        "age_rating": "12세 이용가",
        "price": "무료",
        "favoriteCount": 25262,
        "url": "https://comic.naver.com/webtoon/list?titleId=823536",
        "episode": 43
    },
    {
        "thumbnail": "https://image-comic.pstatic.net/webtoon/652418/thumbnail/thumbnail_IMAG21_7089282876603326775.jpg",
        "rating": 9.97401,
        "id": "652418",
        "type": "웹툰",
        "platform": "네이버 웹툰",
        "title": "파도의 주인",
        "status": "130화 완결",
        "genre": "판타지",
        "views": "-",
        "description": "환상처럼 나타난 두 개의 섬\n그곳에서 나를 맞은 것은 기이한 피부와 붉은 눈을 가진 남자였다.",
        "keywords": [
            "판타지",
            "완결판타지"
        ],
        "author": "이뫄",
        "illustrator": "이뫄",
        "original": "-",
        "age_rating": "전체연령가",
        "price": "24시간 기다리면 무료",
        "favoriteCount": 100787,
        "url": "https://comic.naver.com/webtoon/list?titleId=652418",
        "episode": 130
    },
    {
        "rating": 9.92207,
        "thumbnail": "https://image-comic.pstatic.net/webtoon/814509/thumbnail/thumbnail_IMAG21_59c2f8db-9c88-440c-8911-0cb9814f20f1.jpg",
        "id": "814509",
        "type": "웹툰",
        "platform": "네이버 웹툰",
        "title": "회귀자의 은퇴 라이프",
        "status": "토요웹툰",
        "genre": "판타지",
        "views": "-",
        "description": "2018년 퍼스트 게이트가 열린 이후,\n여러 차원이 연결된 지구에서 임대인은 20년간 살아남았다.\n마침내 맞이한 은퇴식 다음날,\n아무것도 없는 20년 전으로 회귀하게 되는데…",
        "keywords": [
            "사이다",
            "소설원작",
            "판타지",
            "헌터물",
            "이세계",
            "고인물",
            "인외존재",
            "현대판타지",
            "힐링",
            "차원이동",
            "크리처",
            "회귀"
        ],
        "author": "서희",
        "illustrator": "IN사",
        "original": "간짜장",
        "age_rating": "15세 이용가",
        "price": "무료",
        "favoriteCount": 84718,
        "url": "https://comic.naver.com/webtoon/list?titleId=814509",
        "episode": 60
    },
    {
        "rating": 9.90091,
        "thumbnail": "https://image-comic.pstatic.net/webtoon/785701/thumbnail/thumbnail_IMAG21_b93b84ea-264c-47e2-9f55-24e719e65eb9.jpg",
        "id": "785701",
        "type": "웹툰",
        "platform": "네이버 웹툰",
        "title": "가상&RPG",
        "status": "휴재",
        "genre": "판타지",
        "views": "-",
        "description": "\"사람은 좀 죽여도 싸우는건 싫어해요.\" 게임에서조차 집 바깥을 나가지 않는 '제리'. 전투는 한 번도 안해봤는데, 에픽 무기가 귀속되었다? 가상현실 액션 RPG 모브사가 온라인. 그 고인물들의 군상극.",
        "keywords": [
            "2019 최강자전",
            "판타지",
            "고인물",
            "최강자전",
            "게임판타지"
        ],
        "author": "주다현",
        "illustrator": "주다현",
        "original": "-",
        "age_rating": "12세 이용가",
        "price": "무료",
        "favoriteCount": 58702,
        "url": "https://comic.naver.com/webtoon/list?titleId=785701",
        "episode": 60
    },
    {
        "thumbnail": "https://image-comic.pstatic.net/webtoon/497180/thumbnail/thumbnail_IMAG21_3703759224539002420.jpg",
        "rating": 9.9549,
        "id": "497180",
        "type": "웹툰",
        "platform": "네이버 웹툰",
        "title": "언더클래스 히어로",
        "status": "157화 완결",
        "genre": "판타지",
        "views": "-",
        "description": "도시 한가운데서 일어난 정체불명의 대폭발.\n스승의 저주를 받아 천개의 선행을 하게 된 주인공 인(燐), 마을의 원수를 찾아 여행하는 검객 류진(劉進),그리고 정체불명의 약초상 아미(俄靡). 대폭발의 원인을 찾아 떠나는 그들의 여행!",
        "keywords": [
            "히어로",
            "판타지",
            "완결판타지"
        ],
        "author": "김우준",
        "illustrator": "김우준",
        "original": "-",
        "age_rating": "12세 이용가",
        "price": "24시간 기다리면 무료",
        "favoriteCount": 106643,
        "url": "https://comic.naver.com/webtoon/list?titleId=497180",
        "episode": 157
    },
    {
        "rating": 9.96799,
        "thumbnail": "https://image-comic.pstatic.net/webtoon/507638/thumbnail/thumbnail_IMAG21_3690479109175259236.jpg",
        "id": "507638",
        "type": "웹툰",
        "platform": "네이버 웹툰",
        "title": "신령",
        "status": "142화 완결",
        "genre": "판타지",
        "views": "-",
        "description": "신이라 불리는 방울. 그 방울의 선택을 받은 약소국의 어린왕 홍령과\n방울의 비밀을 둘러싼 과거와 현재 이야기.",
        "keywords": [
            "판타지",
            "완결판타지"
        ],
        "author": "이혜",
        "illustrator": "이혜",
        "original": "-",
        "age_rating": "전체연령가",
        "price": "24시간 기다리면 무료",
        "favoriteCount": 344544,
        "url": "https://comic.naver.com/webtoon/list?titleId=507638",
        "episode": 142
    },
    {
        "thumbnail": "https://image-comic.pstatic.net/webtoon/715159/thumbnail/thumbnail_IMAG21_3847537954288906805.jpg",
        "rating": 9.92852,
        "id": "715159",
        "type": "웹툰",
        "platform": "네이버 웹툰",
        "title": "갓핑크",
        "status": "151화 완결",
        "genre": "판타지",
        "views": "-",
        "description": "흥분하면 거대해지는 그놈!\n박성기를 함부로 자극하지 마라​\n생체병기 '핑크맨'의 신체 부위를 나눠가진 초능력자들이 펼치는 박진감 넘치는 액션",
        "keywords": [
            "판타지",
            "완결판타지"
        ],
        "author": "이상신",
        "illustrator": "국중록",
        "original": "-",
        "age_rating": "15세 이용가",
        "price": "24시간 기다리면 무료",
        "favoriteCount": 129740,
        "url": "https://comic.naver.com/webtoon/list?titleId=715159",
        "episode": 151
    },
    {
        "rating": 9.95746,
        "thumbnail": "https://image-comic.pstatic.net/webtoon/188197/thumbnail/thumbnail_IMAG21_7233169362804488545.jpg",
        "id": "188197",
        "type": "웹툰",
        "platform": "네이버 웹툰",
        "title": "미호이야기",
        "status": "27화 완결",
        "genre": "판타지",
        "views": "-",
        "description": "이 세상에 처음 나타난 구미호는 자신의 자식 아홉을 잡아먹어야 \n사람이 된다는 더 웃기지도 않은 저주에 걸린 그저 꼬리가 아홉이나 달린 가여운 숫여우였습니다.",
        "keywords": [
            "판타지",
            "완결판타지",
            "동양풍판타지"
        ],
        "author": "혜진양",
        "illustrator": "혜진양",
        "original": "-",
        "age_rating": "전체연령가",
        "price": "24시간 기다리면 무료",
        "favoriteCount": 63781,
        "url": "https://comic.naver.com/webtoon/list?titleId=188197",
        "episode": 27
    },
    {
        "rating": 9.95469,
        "thumbnail": "https://image-comic.pstatic.net/webtoon/414609/thumbnail/thumbnail_IMAG21_7004281819603612772.jpg",
        "id": "414609",
        "type": "웹툰",
        "platform": "네이버 웹툰",
        "title": "바람이 머무는 난",
        "status": "184화 완결",
        "genre": "판타지",
        "views": "-",
        "description": "어느날 지상 최후의 용과 마주하게 된 한 여자아이의 이야기",
        "keywords": [
            "판타지",
            "완결판타지",
            "다크판타지"
        ],
        "author": "신월",
        "illustrator": "신월",
        "original": "-",
        "age_rating": "12세 이용가",
        "price": "무료",
        "favoriteCount": 169087,
        "url": "https://comic.naver.com/webtoon/list?titleId=414609",
        "episode": 184
    },
    {
        "thumbnail": "https://image-comic.pstatic.net/webtoon/834873/thumbnail/thumbnail_IMAG21_6e480b79-95a1-4211-b6fb-e9dee6302904.jpg",
        "rating": 7.72026,
        "id": "834873",
        "type": "웹툰",
        "platform": "네이버 웹툰",
        "title": "폐급 현자, UR스킬로 인생역전",
        "status": "토요웹툰",
        "genre": "액션",
        "views": "-",
        "description": "다른 세계와 연결되어 '던전'이 나타난 세계.\n신비로운 힘을 각성해 마물을 쓰러뜨리며 생계를 이어가는 사람들은 '모험자'로 불린다.\n키리시마 유토는 사기 직업 '현자'를 얻게되나, 어째서인지 그의 마력은 0! \n공격을 할 수 없는 최약체 현자로서 무시 받는 나날을 보내게 되고, 결국에는 동료에게 버림받아 던전의 희생양으로 던져지는데…\n그런 그의 앞에 나타난 것은 수수께끼의 선택지.\n\"실행하시겠습니까?\" \n그 물음에 답을 하자 능력이 각성하여 과거 현자들의 기술을 다룰 수 있게 되는 UR 스킬 '계승자'가 발동한다.\n최강의 스킬을 손에 넣고, 최강의 모험자로 성장하는 이야기가 시작된다!",
        "keywords": [
            "해외작품",
            "먼치킨",
            "액션판타지",
            "마법",
            "던전물",
            "액션"
        ],
        "author": "아라 아라토",
        "illustrator": "minoru",
        "original": "-",
        "age_rating": "15세 이용가",
        "price": "24시간 기다리면 무료",
        "favoriteCount": 33532,
        "url": "https://comic.naver.com/webtoon/list?titleId=834873",
        "episode": 22
    },
    {
        "rating": 9.81318,
        "thumbnail": "https://image-comic.pstatic.net/webtoon/814421/thumbnail/thumbnail_IMAG21_4915341a-96b4-40a4-828b-805e4eb9ff90.jpg",
        "id": "814421",
        "type": "웹툰",
        "platform": "네이버 웹툰",
        "title": "강철을 먹는 플레이어",
        "status": "수요웹툰",
        "genre": "액션",
        "views": "-",
        "description": "강철대제 이현욱, 인류의 마지막 구원자인 그가 죽었다.\n  미래를 바꾸기 위해 그가 회귀한 곳은… 군대?!!\n왜 하필 여기냐고!”\n  복수를 위해 특급 성장하는 이현욱 상병의 강철 먹방이 시작된다!",
        "keywords": [
            "밀리터리",
            "힘숨찐",
            "헌터물",
            "고인물",
            "이능력배틀물",
            "회귀",
            "액션",
            "상태창",
            "소설원작",
            "인외존재",
            "현대판타지",
            "게임판타지",
            "크리처"
        ],
        "author": "감독9",
        "illustrator": "감독9",
        "original": "지점장",
        "age_rating": "15세 이용가",
        "price": "무료",
        "favoriteCount": 108278,
        "url": "https://comic.naver.com/webtoon/list?titleId=814421",
        "episode": 63
    },
    {
        "rating": 9.93993,
        "thumbnail": "https://image-comic.pstatic.net/webtoon/730694/thumbnail/thumbnail_IMAG21_e6fc219d-e5ea-4d93-b7d6-45b595c2a3cb.jpeg",
        "id": "730694",
        "type": "웹툰",
        "platform": "네이버 웹툰",
        "title": "초인의 시대",
        "status": "휴재",
        "genre": "액션",
        "views": "-",
        "description": "지구에 근원 모를 괴물들이 출현하고\n그들을 제압하는 '초인'들 또한 등장한다.\n정체불명의 괴물과 초인, 바야흐로 '초인의 시대'가 도래한다!",
        "keywords": [
            "판타지",
            "최강자전",
            "소년왕도물",
            "현대",
            "소년물",
            "먼치킨",
            "액션판타지",
            "2018 최강자전",
            "이능력배틀물",
            "액션"
        ],
        "author": "섭이",
        "illustrator": "섭이",
        "original": "-",
        "age_rating": "15세 이용가",
        "price": "무료",
        "favoriteCount": 503144,
        "url": "https://comic.naver.com/webtoon/list?titleId=730694",
        "episode": 189
    },
    {
        "thumbnail": "https://image-comic.pstatic.net/webtoon/829529/thumbnail/thumbnail_IMAG21_3a69f0cc-d6ca-41ea-9bc4-a074cb2a3bc9.jpg",
        "rating": 9.32767,
        "id": "829529",
        "type": "웹툰",
        "platform": "네이버 웹툰",
        "title": "어나더급식느와르",
        "status": "토요웹툰",
        "genre": "액션",
        "views": "-",
        "description": "싸움으로 학교 순위가 매겨지는 시대.\n최고 명문고 삼평고등학교를 재학중인 '진형우'는 싸움을 그만두고 전학을 가기로 결심한다.\n과연 진형우는 자신의 전학을 반대하는 세력을 물리치고 전학을 갈 수 있을것인가?",
        "keywords": [
            "사이다",
            "학원액션",
            "힘숨찐",
            "서바이벌",
            "느와르",
            "고인물",
            "먼치킨",
            "학원물",
            "참교육",
            "병맛",
            "액션"
        ],
        "author": "김진수",
        "illustrator": "김진수",
        "original": "-",
        "age_rating": "15세 이용가",
        "price": "무료",
        "favoriteCount": 10821,
        "url": "https://comic.naver.com/webtoon/list?titleId=829529",
        "episode": 28
    },
    {
        "rating": 9.9525,
        "thumbnail": "https://image-comic.pstatic.net/webtoon/783050/thumbnail/thumbnail_IMAG21_1c2b6455-e424-4c7a-9402-732f0f60a0cb.jpg",
        "id": "783050",
        "type": "웹툰",
        "platform": "네이버 웹툰",
        "title": "신군",
        "status": "105화 완결",
        "genre": "액션",
        "views": "-",
        "description": "악마에게 모든 걸 잃고 먹이로 사육당하는 소년.\n이를 갈며 복수를 갈망하지만 인간의 힘은 악마에게 닿지 못했다.\n그때 그의 앞에 신군이 나타난다.\n2020 지상최대공모전 2기 장려상 수상작!",
        "keywords": [
            "2020 지상최대공모전",
            "완결액션",
            "소년왕도물",
            "액션"
        ],
        "author": "규남",
        "illustrator": "규남",
        "original": "-",
        "age_rating": "15세 이용가",
        "price": "24시간 기다리면 무료",
        "favoriteCount": 101556,
        "url": "https://comic.naver.com/webtoon/list?titleId=783050",
        "episode": 105
    },
    {
        "rating": 9.9804,
        "thumbnail": "https://image-comic.pstatic.net/webtoon/718021/thumbnail/thumbnail_IMAG21_7378080789753586790.jpg",
        "id": "718021",
        "type": "웹툰",
        "platform": "네이버 웹툰",
        "title": "검은인간",
        "status": "81화 완결",
        "genre": "액션",
        "views": "-",
        "description": "너의 흉터도, 너의 두 눈도, 그리고... 너의 힘까지! \n지금부터 모든 걸 바꿔줄게.",
        "keywords": [
            "완결액션",
            "액션"
        ],
        "author": "이저녁",
        "illustrator": "이저녁",
        "original": "-",
        "age_rating": "15세 이용가",
        "price": "24시간 기다리면 무료",
        "favoriteCount": 325295,
        "url": "https://comic.naver.com/webtoon/list?titleId=718021",
        "episode": 81
    },
    {
        "rating": 5.25427,
        "thumbnail": "https://image-comic.pstatic.net/webtoon/833418/thumbnail/thumbnail_IMAG21_e34a17c1-969b-4a11-9c2e-ca933a3113c0.jpg",
        "id": "833418",
        "type": "웹툰",
        "platform": "네이버 웹툰",
        "title": "하이클래스",
        "status": "목요웹툰",
        "genre": "액션",
        "views": "-",
        "description": "고향을 떠나 무작정 서울로 상경한 왕담.\n정착 자금을 받기 위해선 전교 1등을 해야 한다!\n그런데 하필 전학 갈 학교가 공부만 하면 방해하는\n최악들만 모인 일명 '빡고'였는데... 과연 왕담은\n최악의 환경에서 전교 1등을 할 수 있을까?",
        "keywords": [
            "액션"
        ],
        "author": "박만사",
        "illustrator": "르티",
        "original": "-",
        "age_rating": "15세 이용가",
        "price": "무료",
        "favoriteCount": 23127,
        "url": "https://comic.naver.com/webtoon/list?titleId=833418",
        "episode": 19
    },
    {
        "rating": 9.76162,
        "thumbnail": "https://image-comic.pstatic.net/webtoon/720127/thumbnail/thumbnail_IMAG21_3616728296469837412.jpg",
        "id": "720127",
        "type": "웹툰",
        "platform": "네이버 웹툰",
        "title": "쎈놈",
        "status": "94화 완결",
        "genre": "액션",
        "views": "-",
        "description": "왔노라! 싸웠노라! 이겼노라!\n목마른 사슴이 냇가를 찾듯! 최강에 다가서는 그에게 목적과 이유 따윈 없다",
        "keywords": [
            "완결액션",
            "액션"
        ],
        "author": "박용제",
        "illustrator": "박용제",
        "original": "-",
        "age_rating": "12세 이용가",
        "price": "24시간 기다리면 무료",
        "favoriteCount": 103717,
        "url": "https://comic.naver.com/webtoon/list?titleId=720127",
        "episode": 94
    },
    {
        "rating": 9.45591,
        "thumbnail": "https://image-comic.pstatic.net/webtoon/786987/thumbnail/thumbnail_IMAG21_4050198631869998435.jpg",
        "id": "786987",
        "type": "웹툰",
        "platform": "네이버 웹툰",
        "title": "더 퀸즈",
        "status": "41화 완결",
        "genre": "액션",
        "views": "-",
        "description": "\"사람은 사람을 믿을 수 있는가\"\n아동납치와 마약 제조를 일삼는 악명높은 미국의 거대 마피아 '삼부카'\n그들에 맞서기 위해 대한민국의 대재벌 원미호는 불로불사 소녀 강숙희, 마피아 출신 릴리아를 섭외하여 '퀸즈'를 결성한다. \n퀸즈는 삼부카와의 전쟁에서 승리할 수 있을 것인가? \n\n재벌X초인X전직 마피아, 세 여자의 뜨거운 액션!",
        "keywords": [
            "완결액션",
            "슈퍼스트링",
            "액션",
            "걸크러시"
        ],
        "author": "청민",
        "illustrator": "이수현",
        "original": "-",
        "age_rating": "15세 이용가",
        "price": "24시간 기다리면 무료",
        "favoriteCount": 38018,
        "url": "https://comic.naver.com/webtoon/list?titleId=786987",
        "episode": 41
    },
    {
        "thumbnail": "https://image-comic.pstatic.net/webtoon/733765/thumbnail/thumbnail_IMAG21_7220174216941023800.jpg",
        "rating": 9.95405,
        "id": "733765",
        "type": "웹툰",
        "platform": "네이버 웹툰",
        "title": "저세상 클라스!",
        "status": "73화 완결",
        "genre": "액션",
        "views": "-",
        "description": "외모때문에 일진으로 오해받지만 속마음은 여린 최강희에게 싸움고수 할머니 영혼이 빙의되었다?!\n입학하자마자 의강고 서열 1위 일진짱이 된 '최강희'! 무서운 인상과 살벌한 말투에 모두가 그 앞에만 서면 벌벌 떨며 도망치지만... 사실 그는 친구 100명 만들기가 소원인 마음씨 착한 여린 소년이었다!\n어느날 우연히 10년 전에 돌아가신 할머니의 유골함을 떨어트린 손자 강희에게 할머니의 영혼이 빙의되는데...\n핵인싸 싸움고수 할머니가 빙의된 상태로 펼쳐지는 강희의 파란만장한 학교생활! 숨겨진 할머니의 비밀권법! 강희야 가자!!",
        "keywords": [
            "완결액션",
            "액션"
        ],
        "author": "꾀돌이",
        "illustrator": "꾀돌이",
        "original": "-",
        "age_rating": "전체연령가",
        "price": "24시간 기다리면 무료",
        "favoriteCount": 82033,
        "url": "https://comic.naver.com/webtoon/list?titleId=733765",
        "episode": 73
    },
    {
        "thumbnail": "https://image-comic.pstatic.net/webtoon/803541/thumbnail/thumbnail_IMAG21_3fc183ac-11af-4c97-bda5-a35a598f6831.jpg",
        "rating": 9.94826,
        "id": "803541",
        "type": "웹툰",
        "platform": "네이버 웹툰",
        "title": "이야기 들어주는 남자",
        "status": "53화 완결",
        "genre": "스릴러",
        "views": "-",
        "description": "\"방탈출 게임의 특별 규칙, 손님의 숨겨진 과거와 진실을 알아내라\"\n방탈출 시설의 '도우미'로 강제 채용 당한 남자 심우재. 그곳에 끌려온 손님을 도와 목숨을 걸고 탈출해야 한다. 하지만 도우미에겐 손님의 과거와 진실을 알아내야 하는 추가 비밀 미션이 주어지는데... 밝히고 싶지 않은 이야기를 알아내라. <이야기 들어주는 남자>",
        "keywords": [
            "복수극",
            "스릴러",
            "서스펜스",
            "완결스릴러",
            "두뇌싸움"
        ],
        "author": "서진",
        "illustrator": "서진",
        "original": "-",
        "age_rating": "15세 이용가",
        "price": "24시간 기다리면 무료",
        "favoriteCount": 25598,
        "url": "https://comic.naver.com/webtoon/list?titleId=803541",
        "episode": 53
    },
    {
        "thumbnail": "https://image-comic.pstatic.net/webtoon/632705/thumbnail/thumbnail_IMAG21_3905244507107899492.jpg",
        "rating": 9.95102,
        "id": "632705",
        "type": "웹툰",
        "platform": "네이버 웹툰",
        "title": "딥(DEEP)",
        "status": "46화 완결",
        "genre": "스릴러",
        "views": "-",
        "description": "오래 전 실종되었던 가족이 다시 우리 곁으로 돌아왔다!?\n마지막까지 예측불가. 미스터리 드라마 호러 웹툰.",
        "keywords": [
            "스릴러",
            "완결스릴러"
        ],
        "author": "토우",
        "illustrator": "김태헌",
        "original": "-",
        "age_rating": "15세 이용가",
        "price": "24시간 기다리면 무료",
        "favoriteCount": 102776,
        "url": "https://comic.naver.com/webtoon/list?titleId=632705",
        "episode": 46
    },
    {
        "rating": 9.53191,
        "thumbnail": "https://image-comic.pstatic.net/webtoon/258206/thumbnail/thumbnail_IMAG21_7148401404920805686.jpg",
        "id": "258206",
        "type": "웹툰",
        "platform": "네이버 웹툰",
        "title": "LOST",
        "status": "66화 완결",
        "genre": "스릴러",
        "views": "-",
        "description": "주변 사람들의 잇따른 죽음으로 저주 받은 아이라 불리우는 한하제. \n어느 날 그에게 헤어졌던 연인 아리가 찾아 오는데........",
        "keywords": [
            "완결무료",
            "스릴러",
            "완결스릴러"
        ],
        "author": "정민용",
        "illustrator": "정민용",
        "original": "-",
        "age_rating": "12세 이용가",
        "price": "무료",
        "favoriteCount": 26332,
        "url": "https://comic.naver.com/webtoon/list?titleId=258206",
        "episode": 66
    },
    {
        "rating": 9.95316,
        "thumbnail": "https://image-comic.pstatic.net/webtoon/660333/thumbnail/thumbnail_IMAG21_7293353527473365304.JPEG",
        "id": "660333",
        "type": "웹툰",
        "platform": "네이버 웹툰",
        "title": "마야고",
        "status": "34화 완결",
        "genre": "스릴러",
        "views": "-",
        "description": "미스테리 스릴러 빙의,그리고 치명적인 시즌2 마야고!",
        "keywords": [
            "스릴러",
            "완결스릴러"
        ],
        "author": "후렛샤",
        "illustrator": "김홍태",
        "original": "-",
        "age_rating": "15세 이용가",
        "price": "24시간 기다리면 무료",
        "favoriteCount": 100742,
        "url": "https://comic.naver.com/webtoon/list?titleId=660333",
        "episode": 34
    },
    {
        "rating": 9.92099,
        "thumbnail": "https://image-comic.pstatic.net/webtoon/752531/thumbnail/thumbnail_IMAG21_4134920619071780409.jpg",
        "id": "752531",
        "type": "웹툰",
        "platform": "네이버 웹툰",
        "title": "완벽한 가족",
        "status": "55화 완결",
        "genre": "스릴러",
        "views": "-",
        "description": "누가 봐도 행복하고 완벽한 선희네 가족.\n어느 날, 선희는 친구 경호를 죽였다는 고백을 하지만\n엄마의 반응이 뭔가 이상하다.",
        "keywords": [
            "스릴러",
            "완결스릴러"
        ],
        "author": "냥빠",
        "illustrator": "주은",
        "original": "-",
        "age_rating": "15세 이용가",
        "price": "24시간 기다리면 무료",
        "favoriteCount": 111069,
        "url": "https://comic.naver.com/webtoon/list?titleId=752531",
        "episode": 55
    },
    {
        "rating": 9.82805,
        "thumbnail": "https://image-comic.pstatic.net/webtoon/801555/thumbnail/thumbnail_IMAG21_e90dca57-f705-4a4e-8848-752d809b4b8b.jpg",
        "id": "801555",
        "type": "웹툰",
        "platform": "네이버 웹툰",
        "title": "언다잉",
        "status": "61화 완결",
        "genre": "스릴러",
        "views": "-",
        "description": "전국의 죽어가던 노인들의 병이 한순간에 싹 나았다면?\n노인 인구가 급증하고 사회적 비용은 폭발 직전!\n졸지에 노인들을 부양하게 된 젊은 사람들 사이에서 노인들이 버림받고 살해당하는 일도 심심찮게 벌어지게 되는데...\n죽어가던 사람들이 되살아난 기적인 줄 알았지만 재난인 이야기\n죽지않는 노인들, 기적일까 저주일까\n불청객이 되어버린 사람들의 이야기가 시작된다.",
        "keywords": [
            "스릴러",
            "완결스릴러"
        ],
        "author": "임목원",
        "illustrator": "임목원",
        "original": "-",
        "age_rating": "12세 이용가",
        "price": "24시간 기다리면 무료",
        "favoriteCount": 44856,
        "url": "https://comic.naver.com/webtoon/list?titleId=801555",
        "episode": 61
    },
    {
        "thumbnail": "https://image-comic.pstatic.net/webtoon/706770/thumbnail/thumbnail_IMAG21_3761403325765137765.JPEG",
        "rating": 9.82435,
        "id": "706770",
        "type": "웹툰",
        "platform": "네이버 웹툰",
        "title": "언데드",
        "status": "106화 완결",
        "genre": "스릴러",
        "views": "-",
        "description": "대한의 혈청을 통해 회복되는 듯 보이던 좀비 바이러스들에 문제가 생겼다. \n복원센터는 더이상 대한의 혈청이 듣지 않아 난관을 겪고, 대한일행은 석배를 회복시킬 ‘새로운 혈청’을 찾기 위해 무법지대로 떠나지만, 그곳에는 또 다른 시련이 기다리고 있다!",
        "keywords": [
            "스릴러",
            "좀비",
            "완결스릴러"
        ],
        "author": "김우준",
        "illustrator": "김우준",
        "original": "-",
        "age_rating": "15세 이용가",
        "price": "24시간 기다리면 무료",
        "favoriteCount": 92845,
        "url": "https://comic.naver.com/webtoon/list?titleId=706770",
        "episode": 106
    },
    {
        "rating": 9.97084,
        "thumbnail": "https://image-comic.pstatic.net/webtoon/701081/thumbnail/thumbnail_IMAG21_3761692268951647077.jpg",
        "id": "701081",
        "type": "웹툰",
        "platform": "네이버 웹툰",
        "title": "스위트홈",
        "status": "141화 완결",
        "genre": "스릴러",
        "views": "-",
        "description": "절망의 세상을 비관하고 스스로를 고립시킨 한 소년,\n하지만 이제 소년은 밖으로 나가고 싶다.",
        "keywords": [
            "아포칼립스",
            "드라마&영화 원작웹툰",
            "명작",
            "스릴러",
            "완결스릴러"
        ],
        "author": "김칸비",
        "illustrator": "황영찬",
        "original": "-",
        "age_rating": "15세 이용가",
        "price": "24시간 기다리면 무료",
        "favoriteCount": 953136,
        "url": "https://comic.naver.com/webtoon/list?titleId=701081",
        "episode": 141
    },
    {
        "thumbnail": "https://image-comic.pstatic.net/webtoon/647947/thumbnail/thumbnail_IMAG21_4050253636778079542.jpg",
        "rating": 9.97397,
        "id": "647947",
        "type": "웹툰",
        "platform": "네이버 웹툰",
        "title": "저승에서 만난 사람들",
        "status": "29화 완결",
        "genre": "스릴러",
        "views": "-",
        "description": "한 아이의 유괴 사건과 관련된 다섯 사람\n저승에서 펼쳐지는 미스터리 스릴러",
        "keywords": [
            "스릴러",
            "완결스릴러"
        ],
        "author": "단우",
        "illustrator": "백희",
        "original": "-",
        "age_rating": "15세 이용가",
        "price": "24시간 기다리면 무료",
        "favoriteCount": 171066,
        "url": "https://comic.naver.com/webtoon/list?titleId=647947",
        "episode": 29
    },
    {
        "thumbnail": "https://image-comic.pstatic.net/webtoon/675823/thumbnail/thumbnail_IMAG21_3689918564437145954.jpg",
        "rating": 9.94668,
        "id": "675823",
        "type": "웹툰",
        "platform": "네이버 웹툰",
        "title": "감염자",
        "status": "120화 완결",
        "genre": "스릴러",
        "views": "-",
        "description": "사람을 잡아먹는 괴물 '감염자'\n나는 괴물이 되었다.",
        "keywords": [
            "성인웹툰",
            "스릴러",
            "완결스릴러"
        ],
        "author": "이강",
        "illustrator": "이강",
        "original": "-",
        "age_rating": "18세 이용가",
        "price": "24시간 기다리면 무료",
        "favoriteCount": 224837,
        "url": "https://comic.naver.com/webtoon/list?titleId=675823",
        "episode": 120
    },
    {
        "thumbnail": "https://image-comic.pstatic.net/webtoon/783877/thumbnail/thumbnail_IMAG21_0649e854-9113-4a06-a9fe-7cad72be8c9a.jpg",
        "rating": 9.8484,
        "id": "783877",
        "type": "웹툰",
        "platform": "네이버 웹툰",
        "title": "하북팽가 막내아들",
        "status": "화요웹툰",
        "genre": "무협/사극",
        "views": "-",
        "description": "하북팽가 최고의 전력, 도왕 팽지혁. 마교의 습격으로 멸문지화에 빠진 가문을 구하러 낙호곡으로 향하지만 모든 것은 함정이었고, 죽음의 순간 자신이 사랑했던 가문에게 버림받았다는 사실에 분노한다.\n'다시... 내게 한 번만 더 기회가 주어진다면...!'\n죽은 줄 알았던 팽지혁은 방구석 둔재, 하북팽가 사공자의 몸에서 눈을 뜬다.",
        "keywords": [
            "무협/사극",
            "사이다",
            "소설원작",
            "고인물",
            "먼치킨",
            "판무",
            "환생",
            "액션"
        ],
        "author": "스튜디오 시그마",
        "illustrator": "기원",
        "original": "무향",
        "age_rating": "15세 이용가",
        "price": "무료",
        "favoriteCount": 134963,
        "url": "https://comic.naver.com/webtoon/list?titleId=783877",
        "episode": 168
    },
    {
        "rating": 9.92626,
        "thumbnail": "https://image-comic.pstatic.net/webtoon/827322/thumbnail/thumbnail_IMAG21_11e2cfaf-c327-457e-8b33-a79f0b1e9252.jpg",
        "id": "827322",
        "type": "웹툰",
        "platform": "네이버 웹툰",
        "title": "무벌전",
        "status": "월요웹툰",
        "genre": "무협/사극",
        "views": "-",
        "description": "…무당이 망했다!!!\n\n긴 임무에서 돌아온 2대제자 충엽. 그러나 본산은 이미 폐허가 되고, 이에 절망한 충엽도 폐인이 되었다!\n그러나 아직 한 줄기 희망을 품고 있는 석현과 무영!\n과연 무당의 앞날은 어찌 될 것인지…. 이 녀석 충엽! 어서 의욕 좀 챙겨라!! 이 벌레야!!!",
        "keywords": [
            "무협/사극",
            "정통무협",
            "소년왕도물",
            "성장물",
            "2022 지상최대공모전",
            "시대물",
            "복수극",
            "동양",
            "액션"
        ],
        "author": "노백",
        "illustrator": "노백",
        "original": "-",
        "age_rating": "15세 이용가",
        "price": "무료",
        "favoriteCount": 58126,
        "url": "https://comic.naver.com/webtoon/list?titleId=827322",
        "episode": 36
    },
    {
        "rating": 9.90814,
        "thumbnail": "https://image-comic.pstatic.net/webtoon/63453/thumbnail/thumbnail_IMAG21_7018072108335194469.jpg",
        "id": "63453",
        "type": "웹툰",
        "platform": "네이버 웹툰",
        "title": "묵회",
        "status": "112화 완결",
        "genre": "무협/사극",
        "views": "-",
        "description": "떠돌이 점쟁이 모아의 이야기.\n \r\n그녀가 만나는 사람들의 이야기. 그리고 우리의 이야기. 이 세상의 이야기",
        "keywords": [
            "무협/사극",
            "완결무료",
            "완결무협/사극"
        ],
        "author": "한나",
        "illustrator": "한나",
        "original": "-",
        "age_rating": "전체연령가",
        "price": "무료",
        "favoriteCount": 9231,
        "url": "https://comic.naver.com/webtoon/list?titleId=63453",
        "episode": 112
    },
    {
        "rating": 9.93402,
        "thumbnail": "https://image-comic.pstatic.net/webtoon/746857/thumbnail/thumbnail_IMAG21_9a0d4005-34a6-4fb5-a9dc-61a305cb580d.jpg",
        "id": "746857",
        "type": "웹툰",
        "platform": "네이버 웹툰",
        "title": "무사만리행",
        "status": "목요웹툰",
        "genre": "무협/사극",
        "views": "-",
        "description": "콤모두스 황제와의 혈투 후 3년, 나루는 다시 한번 모든 것을 잃었다.",
        "keywords": [
            "무협/사극",
            "성장물",
            "퓨전사극",
            "먼치킨",
            "판무"
        ],
        "author": "운",
        "illustrator": "배민기",
        "original": "-",
        "age_rating": "15세 이용가",
        "price": "무료",
        "favoriteCount": 234990,
        "url": "https://comic.naver.com/webtoon/list?titleId=746857",
        "episode": 213
    },
    {
        "rating": 9.86053,
        "thumbnail": "https://image-comic.pstatic.net/webtoon/400735/thumbnail/thumbnail_IMAG21_7219661874503301217.jpg",
        "id": "400735",
        "type": "웹툰",
        "platform": "네이버 웹툰",
        "title": "한섬세대",
        "status": "41화 완결",
        "genre": "무협/사극",
        "views": "-",
        "description": "조선후기의 평범한 관리지망생 한섬. \n\r\n만만치 않은 길이지만, 한섬이는 만만디. 과연 벼슬자리에 오를 수 있을까?",
        "keywords": [
            "무협/사극",
            "역사물",
            "완결무료",
            "완결무협/사극"
        ],
        "author": "유승진",
        "illustrator": "유승진",
        "original": "-",
        "age_rating": "전체연령가",
        "price": "무료",
        "favoriteCount": 10340,
        "url": "https://comic.naver.com/webtoon/list?titleId=400735",
        "episode": 41
    },
    {
        "rating": 9.95082,
        "thumbnail": "https://image-comic.pstatic.net/webtoon/784417/thumbnail/thumbnail_IMAG21_f997ffe9-465a-4be8-a0bb-b5d0ef5cedea.jpg",
        "id": "784417",
        "type": "웹툰",
        "platform": "네이버 웹툰",
        "title": "무림서부",
        "status": "휴재",
        "genre": "무협/사극",
        "views": "-",
        "description": "황제가 무공을 통한 철혈정치로 제국을 천년동안 유지함에 따라, 오로지 황군 무공만이 힘이요 법도로 살아남고, 고전 무공들은 스러지고 만다. 이런 세계에 환생한 무협지 마니아, 주인공 장건. 과연 그는 동경하던 고전 무공을 되살릴 수 있을까. 서부 대륙 개척지에서 벌어지는 정통 무협의 정수!",
        "keywords": [
            "무협/사극",
            "소설원작",
            "힘숨찐",
            "세계관",
            "판무"
        ],
        "author": "임팩",
        "illustrator": "정한길",
        "original": "컵라면.",
        "age_rating": "15세 이용가",
        "price": "무료",
        "favoriteCount": 77188,
        "url": "https://comic.naver.com/webtoon/list?titleId=784417",
        "episode": 63
    },
    {
        "rating": 9.94885,
        "thumbnail": "https://image-comic.pstatic.net/webtoon/796075/thumbnail/thumbnail_IMAG21_31f75c4c-81c9-454a-8d92-9e23b577e1a5.jpg",
        "id": "796075",
        "type": "웹툰",
        "platform": "네이버 웹툰",
        "title": "절대검감",
        "status": "월요웹툰",
        "genre": "무협/사극",
        "views": "-",
        "description": "단전이 부숴졌다는 이유로 집에서는 내놓은 자식 취급을 받던 소운휘는 혈교에 납치되어서도 삼류 첩자로 살아왔다.\n어느 날, 전설로만 알려진 검선비록을 찾는데 이용당하다 죽은 운휘는 10년 전, 혈교에 납치되던 그 날로 돌아가게 되고 검의 목소리를 듣는 신비한 능력을 얻는다.",
        "keywords": [
            "무협/사극",
            "소설원작",
            "성장물",
            "환골탈태",
            "이능력",
            "모험",
            "먼치킨",
            "복수극",
            "동양",
            "회귀",
            "판무",
            "액션"
        ],
        "author": "김두루미",
        "illustrator": "티아이",
        "original": "한중월야",
        "age_rating": "12세 이용가",
        "price": "무료",
        "favoriteCount": 211548,
        "url": "https://comic.naver.com/webtoon/list?titleId=796075",
        "episode": 119
    },
    {
        "thumbnail": "https://image-comic.pstatic.net/webtoon/817246/thumbnail/thumbnail_IMAG21_0cca8109-c5c2-4a25-91b3-0b338a73e59d.jpg",
        "rating": 9.9713,
        "id": "817246",
        "type": "웹툰",
        "platform": "네이버 웹툰",
        "title": "할배무사와 지존 손녀",
        "status": "목요웹툰",
        "genre": "무협/사극",
        "views": "-",
        "description": "죽을 날을 앞두고 미련없이 생을 마무리 하려던 순간 덮친 멸문지화!\n유진산은 홀로 생존한 갓난 손녀 '유설'이 다 자랄 때까지만이라도 살아남기로 결심한다.\n이미 늙어버린 몸으로 육아와 수련을 병행하며 눈물겨운 사투를 벌이는 동안,\n어느새 무림지존의 기재를 타고난 손녀는 믿을 수 없이 빠르게 성장해가고 있었다.\n\"걱정마, 할배. 이젠 내가 지켜줄게!\"",
        "keywords": [
            "무협/사극",
            "소설원작",
            "정통무협",
            "가족",
            "고인물",
            "성장물",
            "모험",
            "먼치킨",
            "육아물",
            "액션"
        ],
        "author": "신의철",
        "illustrator": "김명현",
        "original": "일향(一向)",
        "age_rating": "전체연령가",
        "price": "무료",
        "favoriteCount": 124033,
        "url": "https://comic.naver.com/webtoon/list?titleId=817246",
        "episode": 77
    },
    {
        "rating": 9.75134,
        "thumbnail": "https://image-comic.pstatic.net/webtoon/813443/thumbnail/thumbnail_IMAG21_0151f856-8505-4575-b935-b309e873e034.jpg",
        "id": "813443",
        "type": "웹툰",
        "platform": "네이버 웹툰",
        "title": "황제의 검",
        "status": "휴재",
        "genre": "무협/사극",
        "views": "-",
        "description": "정난의 변에서 간신히 살아난 주윤문,\n마교 천하제일 천마(天魔)와 소림사 육조 혜능(慧能)을 몸 안에 받아\n천마서생 '파천'으로 재탄생하게 되는데…\n절대지존을 향한 파천의 새로운 이야기가 시작된다!",
        "keywords": [
            "전쟁",
            "이세계",
            "성장물",
            "신화",
            "서양",
            "동양",
            "액션",
            "무협/사극",
            "소설원작",
            "인외존재",
            "먼치킨",
            "크리처",
            "참교육",
            "판무"
        ],
        "author": "레드훅",
        "illustrator": "류신",
        "original": "임무성",
        "age_rating": "전체연령가",
        "price": "무료",
        "favoriteCount": 95835,
        "url": "https://comic.naver.com/webtoon/list?titleId=813443",
        "episode": 63
    },
    {
        "rating": 9.91745,
        "thumbnail": "https://image-comic.pstatic.net/webtoon/748536/thumbnail/thumbnail_IMAG21_f5ccf206-ed7d-42ae-9452-c11cb188474b.jpg",
        "id": "748536",
        "type": "웹툰",
        "platform": "네이버 웹툰",
        "title": "사상최강",
        "status": "188화 완결",
        "genre": "무협/사극",
        "views": "-",
        "description": "‘천하 십대 고수’라고 불리는 자들. 인간의 한계를 뛰어넘은 그들은 서로를 견제하며 힘의 균형과 세상의 질서를 유지해왔다.\n바로 ‘백도현’ 그가 나타나기 전까지는! 내공만으로 사상최강의 힘을 가진 남자 백도현의 시원한 한 방!",
        "keywords": [
            "무협/사극",
            "사이다",
            "소설원작",
            "정통무협",
            "로맨스",
            "가벼운",
            "먼치킨",
            "완결무협/사극",
            "개그",
            "동양"
        ],
        "author": "이단아",
        "illustrator": "이단아",
        "original": "황규영",
        "age_rating": "전체연령가",
        "price": "24시간 기다리면 무료",
        "favoriteCount": 130201,
        "url": "https://comic.naver.com/webtoon/list?titleId=748536",
        "episode": 188
    },
    {
        "rating": 9.93976,
        "thumbnail": "https://image-comic.pstatic.net/webtoon/834511/thumbnail/thumbnail_IMAG21_34c69a2c-088a-44c2-93d1-e899c1881b47.jpg",
        "id": "834511",
        "type": "웹툰",
        "platform": "네이버 웹툰",
        "title": "트럭기사 태그배 경",
        "status": "월요웹툰",
        "genre": "개그",
        "views": "-",
        "description": "밤늦게까지 이어진 알바를 드디어 끝내고 집으로 돌아가는 길, \n지친 현실에서도 나의 유일한 안식처가 되어준 건\n수십 번 정주행하고 있는 로맨스 판타지 소설이었다.\n\n평소처럼 소설을 보며 걷다 트럭에 치여버릴 뻔한 순간…!\n\n응? 왜인지 소설 속으로 들어와버린 트럭기사 택진 씨의\n원래 세계로 돌아가기 위한 고군분투가 시작된다!",
        "keywords": [
            "로판",
            "구원서사",
            "치명적인",
            "개그",
            "중년",
            "햇살녀",
            "왕족/귀족",
            "판타지개그",
            "중세"
        ],
        "author": "마자",
        "illustrator": "마자",
        "original": "-",
        "age_rating": "전체연령가",
        "price": "무료",
        "favoriteCount": 15551,
        "url": "https://comic.naver.com/webtoon/list?titleId=834511",
        "episode": 12
    },
    {
        "thumbnail": "https://image-comic.pstatic.net/webtoon/541901/thumbnail/thumbnail_IMAG21_3762818380137062962.jpg",
        "rating": 9.61633,
        "id": "541901",
        "type": "웹툰",
        "platform": "네이버 웹툰",
        "title": "마인드컨트롤",
        "status": "37화 완결",
        "genre": "개그",
        "views": "-",
        "description": "살면서 누구나 한번쯤 가져봤을 궁금증을 마음과 심리를 꿰뚫는 공감으로 해결한다?!\r\n\n본 컨텐츠는 SBS TV프로그램 <화신>과 함께하는 제휴 웹툰입니다.",
        "keywords": [
            "완결무료",
            "완결개그",
            "개그"
        ],
        "author": "마인드C",
        "illustrator": "마인드C",
        "original": "-",
        "age_rating": "전체연령가",
        "price": "무료",
        "favoriteCount": 17385,
        "url": "https://comic.naver.com/webtoon/list?titleId=541901",
        "episode": 37
    },
    {
        "rating": 9.94264,
        "thumbnail": "https://image-comic.pstatic.net/webtoon/663681/thumbnail/thumbnail_IMAG21_7147886824839013732.jpg",
        "id": "663681",
        "type": "웹툰",
        "platform": "네이버 웹툰",
        "title": "가우스 임파서블",
        "status": "8화 완결",
        "genre": "개그",
        "views": "-",
        "description": "본 컨텐츠는 곽백수 작가가 전하는 산업재해 예방 캠페인으로서 안전보건공단의 브랜드 웹툰입니다.",
        "keywords": [
            "완결무료",
            "완결개그",
            "개그"
        ],
        "author": "곽백수",
        "illustrator": "곽백수",
        "original": "-",
        "age_rating": "전체연령가",
        "price": "무료",
        "favoriteCount": 6144,
        "url": "https://comic.naver.com/webtoon/list?titleId=663681",
        "episode": 8
    },
    {
        "rating": 9.90641,
        "thumbnail": "https://image-comic.pstatic.net/webtoon/511444/thumbnail/thumbnail_IMAG21_7293970357788095588.JPEG",
        "id": "511444",
        "type": "웹툰",
        "platform": "네이버 웹툰",
        "title": "버프소녀 오오라",
        "status": "100화 완결",
        "genre": "개그",
        "views": "-",
        "description": "'정글고', '쌉니다 천리마마트' Q3작가의 스마트툰 신작!\n버프가 필요한 당신을 위하여.",
        "keywords": [
            "완결개그",
            "개그"
        ],
        "author": "김규삼",
        "illustrator": "김규삼",
        "original": "-",
        "age_rating": "12세 이용가",
        "price": "무료",
        "favoriteCount": 121100,
        "url": "https://comic.naver.com/webtoon/list?titleId=511444",
        "episode": 100
    },
    {
        "thumbnail": "https://image-comic.pstatic.net/webtoon/22052/thumbnail/thumbnail_IMAG21_4123380150160340279.jpg",
        "rating": 9.91579,
        "id": "22052",
        "type": "웹툰",
        "platform": "네이버 웹툰",
        "title": "트라우마",
        "status": "371화 완결",
        "genre": "개그",
        "views": "-",
        "description": "황당하고 골 때리는 반전! \n\r\nTrauma(-정신적 외상)를 입을 만한 초특급 코믹 펀치! 직접 확인하세요",
        "keywords": [
            "완결무료",
            "완결개그",
            "개그"
        ],
        "author": "곽백수",
        "illustrator": "곽백수",
        "original": "-",
        "age_rating": "12세 이용가",
        "price": "무료",
        "favoriteCount": 19285,
        "url": "https://comic.naver.com/webtoon/list?titleId=22052",
        "episode": 371
    },
    {
        "rating": 9.94707,
        "thumbnail": "https://image-comic.pstatic.net/webtoon/794210/thumbnail/thumbnail_IMAG21_7234016187832755042.jpg",
        "id": "794210",
        "type": "웹툰",
        "platform": "네이버 웹툰",
        "title": "죄송한데 주인공이세요?",
        "status": "27화 완결",
        "genre": "개그",
        "views": "-",
        "description": "꼴찌 성적의 로맨스물을 연재 중인 웹툰 작가 정은하. \n인기 있는 만화를 그리고 싶다는 염원을 담아 연필을 집어든 은하는 본인의 만화 속에서 깨어나게 되고\n기왕 만화 속으로 들어온 거, 내용을 전부 뜯어고쳐서 인기 순위권에 들려 하는데..\n그렇다면 가장 먼저 해야 할 일은.. 로맨스가 일어나지 않도록 남주를 죽이는 것?!\n\"이 만화는 오늘부터 학원 폭력물로 장르를 바꾼다!!\"",
        "keywords": [
            "완결개그",
            "개그"
        ],
        "author": "조석",
        "illustrator": "조석",
        "original": "-",
        "age_rating": "전체연령가",
        "price": "24시간 기다리면 무료",
        "favoriteCount": 72854,
        "url": "https://comic.naver.com/webtoon/list?titleId=794210",
        "episode": 27
    },
    {
        "rating": 9.8795,
        "thumbnail": "https://image-comic.pstatic.net/webtoon/668948/thumbnail/thumbnail_IMAG21_4121135849342853733.jpg",
        "id": "668948",
        "type": "웹툰",
        "platform": "네이버 웹툰",
        "title": "코드명 가우스",
        "status": "8화 완결",
        "genre": "개그",
        "views": "-",
        "description": "본 컨텐츠는 비씨카드㈜의 브랜드 웹툰으로 곽백수 작가가 전하는 BC페이 소개입니다.\n가우스 첩보원의 위기!!\n새롭게 탑재한 페이로 위기를 탈출하라!!",
        "keywords": [
            "완결무료",
            "완결개그",
            "개그"
        ],
        "author": "곽백수",
        "illustrator": "곽백수",
        "original": "-",
        "age_rating": "전체연령가",
        "price": "무료",
        "favoriteCount": 3756,
        "url": "https://comic.naver.com/webtoon/list?titleId=668948",
        "episode": 8
    },
    {
        "thumbnail": "https://image-comic.pstatic.net/webtoon/651665/thumbnail/thumbnail_IMAG21_7293352204737930595.jpg",
        "rating": 9.84183,
        "id": "651665",
        "type": "웹툰",
        "platform": "네이버 웹툰",
        "title": "야부리맨",
        "status": "136화 완결",
        "genre": "개그",
        "views": "-",
        "description": "말하는대로 모든 것이 이루어진다?! \n역대급 슈퍼히어로의 초특급 재능낭비! \n미티 작가의 컷툰 신작",
        "keywords": [
            "완결무료",
            "완결개그",
            "개그"
        ],
        "author": "미티",
        "illustrator": "미티",
        "original": "-",
        "age_rating": "12세 이용가",
        "price": "무료",
        "favoriteCount": 115219,
        "url": "https://comic.naver.com/webtoon/list?titleId=651665",
        "episode": 136
    },
    {
        "thumbnail": "https://image-comic.pstatic.net/webtoon/740423/thumbnail/thumbnail_IMAG21_4050763990542279216.jpg",
        "rating": 9.82503,
        "id": "740423",
        "type": "웹툰",
        "platform": "네이버 웹툰",
        "title": "도전 K-스타트업",
        "status": "8화 완결",
        "genre": "개그",
        "views": "-",
        "description": "본 컨텐츠는 중소벤처기업부와 창업진흥원의 브랜드 웹툰으로 곽백수 작가가 전하는 창업경진대회 이야기입니다.",
        "keywords": [
            "완결무료",
            "완결개그",
            "개그"
        ],
        "author": "곽백수",
        "illustrator": "곽백수",
        "original": "-",
        "age_rating": "전체연령가",
        "price": "무료",
        "favoriteCount": 2285,
        "url": "https://comic.naver.com/webtoon/list?titleId=740423",
        "episode": 8
    },
    {
        "thumbnail": "https://image-comic.pstatic.net/webtoon/186814/thumbnail/thumbnail_IMAG21_3775482378130187572.jpg",
        "rating": 9.63295,
        "id": "186814",
        "type": "웹툰",
        "platform": "네이버 웹툰",
        "title": "심부름센터 K",
        "status": "24화 완결",
        "genre": "개그",
        "views": "-",
        "description": "수사9단의 김선권 작가의 신작.특별한 능력을 가진 직원들의 엉뚱하고도 황당한 임무 해결.\n",
        "keywords": [
            "완결무료",
            "완결개그",
            "개그"
        ],
        "author": "김선권",
        "illustrator": "김선권",
        "original": "-",
        "age_rating": "12세 이용가",
        "price": "무료",
        "favoriteCount": 9978,
        "url": "https://comic.naver.com/webtoon/list?titleId=186814",
        "episode": 24
    }
    
]